pipgen/__init__.py
pipgen/wrapper.py
pipgen-0.2.2.data/scripts/depipify.sh
pipgen-0.2.2.data/scripts/pipify.sh
pipgen-0.2.2.data/scripts/pippush.sh
pipgen-0.2.2.dist-info/METADATA
pipgen-0.2.2.dist-info/WHEEL
pipgen-0.2.2.dist-info/top_level.txt
pipgen-0.2.2.dist-info/RECORD
