Metadata-Version: 2.1
Name: pipgen
Version: 0.2.2
Summary: A package for easily creating and distributing pip packages.
Home-page: https://github.com/caseyjohnsonwv/pip-package-generator
Author: Casey Johnson
Author-email: ctj0001@mix.wvu.edu
License: UNKNOWN
Platform: UNKNOWN
Classifier: Programming Language :: Python :: 3
Classifier: License :: OSI Approved :: MIT License
Classifier: Operating System :: OS Independent
Requires-Dist: twine
Requires-Dist: setuptools
Requires-Dist: wheel
